kamma/__init__.py
kamma/app.py
kamma/queue.py
kamma/task.py
kamma-0.0.10.dist-info/zip-safe
kamma-0.0.10.dist-info/top_level.txt
kamma-0.0.10.dist-info/METADATA
kamma-0.0.10.dist-info/DESCRIPTION.rst
kamma-0.0.10.dist-info/metadata.json
kamma-0.0.10.dist-info/WHEEL
kamma-0.0.10.dist-info/RECORD
